{"lastUsed":1616604254956,"path":"E:\/Kando\/6_felev\/projekt2\/program","projectCount":1,"recentFiles":[{"path":"\/robotarm2_test\/Core\/Src","parentWorkspace":"E:\/Kando\/6_felev\/projekt2\/program","name":"main.c","lastModified":1616603147102,"locationURI":"file:\/E:\/Kando\/6_felev\/projekt2\/program\/robotarm2_test\/Core\/Src\/main.c"},{"path":"\/robotarm2_test\/Core\/Src","parentWorkspace":"E:\/Kando\/6_felev\/projekt2\/program","name":"lcd.c","lastModified":1616604254959,"locationURI":"file:\/E:\/Kando\/6_felev\/projekt2\/program\/robotarm2_test\/Core\/Src\/lcd.c"}]}